{
  "876f12e6fa1118564ed4cd36216ce8c4d21dbecf.png": {
    "title": "Meta.png",
    "description": "Meta.png",
    "tags": [
      {
        "title": "CIAPIE",
        "_id": "5f874c1bb1179b13bc9f5585"
      }
    ]
  },
  "b3f3dabfe4652d6bc35de7c97d614c0e4f57d4a7.jpg": {
    "title": "Block 1 - Century skill.jpg",
    "description": "Block 1 - Century skill.jpg",
    "tags": [
      {
        "title": "CIAPIE",
        "_id": "5f874c1bb1179b13bc9f5585"
      }
    ]
  },
  "aa7c3152f02f6419e35b61a639624be819bad1de.jpg": {
    "title": "Block 2 - Century skill.jpg",
    "description": "Block 2 - Century skill.jpg",
    "tags": [
      {
        "title": "CIAPIE",
        "_id": "5f874c1bb1179b13bc9f5585"
      }
    ]
  },
  "348042e1343048f1646e2eb050eb83f3501517c9.jpg": {
    "title": "Block 3 - Century skill.jpg",
    "description": "Block 3 - Century skill.jpg",
    "tags": [
      {
        "title": "CIAPIE",
        "_id": "5f874c1bb1179b13bc9f5585"
      }
    ]
  },
  "eed46fc4756edd4184c24eb08addefd8b6a6ca5a.jpg": {
    "title": "Block 4 - Century skill.jpg",
    "description": "Block 4 - Century skill.jpg",
    "tags": [
      {
        "title": "CIAPIE",
        "_id": "5f874c1bb1179b13bc9f5585"
      }
    ]
  },
  "711276b12ea8e4a74afc14f0c01c86752f6c79eb.jpg": {
    "title": "Block 5 - Century skill.jpg",
    "description": "Block 5 - Century skill.jpg",
    "tags": [
      {
        "title": "CIAPIE",
        "_id": "5f874c1bb1179b13bc9f5585"
      }
    ]
  },
  "cdbca327846c0bd649daeee6a7b97faa56afb8d5.jpg": {
    "title": "Block 6 - Century skill.jpg",
    "description": "Block 6 - Century skill.jpg",
    "tags": [
      {
        "title": "CIAPIE",
        "_id": "5f874c1bb1179b13bc9f5585"
      }
    ]
  },
  "a9c7df37eba6fbe9289afc3e78b63a5abe3476ea.jpg": {
    "title": "Century Skill 1.jpg",
    "description": "Century Skill 1.jpg",
    "tags": [
      {
        "title": "CIAPIE",
        "_id": "5f874c1bb1179b13bc9f5585"
      }
    ]
  },
  "2e163bdf525ff0f6eb2a3a1b2c7fb922f180766f.jpg": {
    "title": "Century Skill 2.jpg",
    "description": "Century Skill 2.jpg",
    "tags": [
      {
        "title": "CIAPIE",
        "_id": "5f874c1bb1179b13bc9f5585"
      }
    ]
  },
  "6116938b4ceabe677aa307d7294ab7b02ff2eba3.jpg": {
    "title": "Century Skill 3.jpg",
    "description": "Century Skill 3.jpg",
    "tags": [
      {
        "title": "CIAPIE",
        "_id": "5f874c1bb1179b13bc9f5585"
      }
    ]
  },
  "ec3411d3423f8187f07cec69cce3bb44a1bb8259.jpg": {
    "title": "Century Skill 4.jpg",
    "description": "Century Skill 4.jpg",
    "tags": [
      {
        "title": "CIAPIE",
        "_id": "5f874c1bb1179b13bc9f5585"
      }
    ]
  }
}